g11npy/__init__.py
g11npy/__version__.py
g11npy/base.py
g11npy/constants.py
g11npy/dict_based.py
g11npy/hooks.py
g11npy/noop.py
g11npy-0.1.1.dist-info/LICENSE
g11npy-0.1.1.dist-info/METADATA
g11npy-0.1.1.dist-info/WHEEL
g11npy-0.1.1.dist-info/top_level.txt
g11npy-0.1.1.dist-info/RECORD
