Metadata-Version: 2.1
Name: g11npy
Version: 0.1.1
Summary: Internationalization and localization tools.
Home-page: https://github.com/TNick/g11n
Download-URL: https://github.com/TNick/g11n/archive/v0.1.1.zip
Author: Nicu Tofan
Author-email: nicu.tofan@gmail.com
License: MIT
Project-URL: Bug Tracker, https://github.com/TNick/g11n/issues
Project-URL: Documentation, https://github.com/TNick/g11n
Project-URL: Source Code, https://github.com/TNick/g11n
Classifier: Development Status :: 3 - Alpha
Classifier: Intended Audience :: Developers
Classifier: License :: OSI Approved :: MIT License
Classifier: Programming Language :: Python
Classifier: Programming Language :: Python :: 3
Classifier: Programming Language :: Python :: 3.6
Classifier: Programming Language :: Python :: Implementation :: CPython
Classifier: Programming Language :: Python :: Implementation :: PyPy
Requires-Python: >=3.6.0
License-File: LICENSE
Requires-Dist: pluggy (>=1.0.0)
Provides-Extra: dev
Requires-Dist: pytest ; extra == 'dev'
Requires-Dist: twine ; extra == 'dev'
Requires-Dist: devpi-client ; extra == 'dev'
Requires-Dist: wheel ; extra == 'dev'
Requires-Dist: sphinx ; extra == 'dev'
Requires-Dist: sphinx-rtd-theme ; extra == 'dev'
Requires-Dist: recommonmark ; extra == 'dev'
Requires-Dist: m2r ; extra == 'dev'
Requires-Dist: coverage ; extra == 'dev'
Provides-Extra: tests
Requires-Dist: mock ; extra == 'tests'
Requires-Dist: pytest ; extra == 'tests'
